uploadio_sdk/__init__.py
uploadio_sdk/main.py
uploadio_sdk/schemas/__init__.py
uploadio_sdk/schemas/get_file_urls_schema.py
uploadio_sdk/services/__init__.py
uploadio_sdk/services/base_service.py
uploadio_sdk/services/get_file_urls/__init__.py
uploadio_sdk/services/get_file_urls/get_file_urls_service.py
uploadio_sdk-0.0.3.dist-info/LICENSE
uploadio_sdk-0.0.3.dist-info/METADATA
uploadio_sdk-0.0.3.dist-info/WHEEL
uploadio_sdk-0.0.3.dist-info/top_level.txt
uploadio_sdk-0.0.3.dist-info/RECORD
